[
    {
        "networt": "arbitrum",
        "name": "Arbitrum One",
        "info": {
            "url": "https://arbitrum.io/",
            "chainId": "42161"
        }
    },
    {
        "networt": "avalanche",
        "name": "Avalanche C-Chain",
        "info": {
            "url": "https://www.avax.network/",
            "chainId": "43114"
        }
    },
    {
        "networt": "base",
        "name": "Base",
        "info": {
            "url": "https://www.base.org/",
            "chainId": "8453"
        }
    },
    {
        "networt": "bep20",
        "name": "BNB Smart Chain",
        "info": {
            "url": "https://www.bnbchain.org",
            "chainId": "56"
        }
    },
    {
        "networt": "bitcoin",
        "name": "Bitcoin",
        "info": {
            "url": "https://bitcoin.org"
        }
    },
    {
        "networt": "erc20",
        "name": "Ethereum",
        "info": {
            "url": "https://bitcoin.org",
            "chainId": "1"
        }
    },
    {
        "networt": "lightning-network",
        "name": "Lightning Network",
        "info": {
            "url": "https://lightning.network/"
        }
    },
    {
        "networt": "optimism",
        "name": "Optimism",
        "info": {
            "url": "https://www.optimism.io/",
            "chainId": "10"
        }
    },
    {
        "networt": "polygon",
        "name": "Polygon",
        "info": {
            "url": "https://polygon.technology/",
            "chainId": "137"
        }
    },
    {
        "networt": "stellar",
        "name": "Stellar",
        "info": {
            "url": "https://stellar.org"
        }
    },
    {
        "networt": "solana",
        "name": "Solana",
        "info": {
            "url": "https://solana.com"
        }
    },
    {
        "networt": "trc20",
        "name": "Tron",
        "info": {
            "url": "https://www.tron.org/"
        }
    }
]